{
    "物件名称": "ヒューリック蛎殻町ビル",
    "分類": "東京コマーシャル・プロパティ（オフィス)",
    "特定資産の概要": {
        "特定資産の種類": "信託受益権",
        "信託受益権の概要": {
            "信託受託者": "みずほ信託銀行株式会社",
            "信託設定日": "2014年２月７日",
            "信託期間満了日": "2034年２月28日"
        },
        "取得年月日": "2014年２月７日",
        "取得価格": "2,210百万円",
        "最寄駅": "東京メトロ半蔵門線「水天宮前」駅　徒歩２分",
        "所在地（住居表示）": "東京都中央区日本橋蛎殻町一丁目28番５号",
        "土地": {
            "地番": "東京都中央区日本橋蛎殻町一丁目28番４他",
            "建蔽率": "100％（注）",
            "容積率": "700％",
            "用途地域": "商業地域",
            "敷地面積": "683.17㎡",
            "所有形態": "所有権"
        },
        "建物": {
            "竣工年月": "1993年３月",
            "構造": "鉄骨鉄筋コンクリート造",
            "階数": "地上９階地下１階",
            "用途": "銀行・事務所・車庫",
            "延床面積": "4,345.12㎡",
            "所有形態": "所有権"
        },
        "PM会社": "ヒューリック株式会社",
        "マスターリース会社": "ヒューリック株式会社"
    },
    "タイトル未定義(1)": "特記事項\n該当ありません。",
    "賃貸借の概要": {
        "代表的テナント": "―",
        "テナント数": "10"
    },
    "タイトル未定義(2)": "（注）本物件の土地の指定建蔽率は本来80％ですが、防火地域内にある耐火建築物であることから適用される建蔽率は100％となります。"
}