{
    "物件番号": "OFC-09",
    "物件名称": "博多駅イーストプレイス",
    "分類": "オフィス",
    "特定資産の概要": {
        "特定資産の種類": "信託受益権",
        "信託受託者": "三井住友信託銀行株式会社",
        "取得価格": "2,286百万円",
        "取得日": "2017年4月6日",
        "所在地": "福岡県福岡市博多区博多駅東三丁目15番2 ほか",
        "住居表示": "福岡県福岡市博多区博多駅東3-1-26",
        "最寄駅": "JR線・福岡市営地下鉄空港線「博多」駅徒歩約10分",
        "土地": {
            "所有形態": "所有権",
            "敷地面積": "1,129.86㎡",
            "用途地域": "商業地域",
            "建蔽率": "80％",
            "容積率": "500％(注)"
        },
        "建物": {
            "所有形態": "所有権",
            "延床面積": "6,243.13㎡(駐車場:94.00㎡を含む)",
            "用途": "事務所",
            "建築時期": "1986年2月24日",
            "構造・階数": "鉄骨鉄筋コンクリート造陸屋根9階建"
        },
        "PM会社": "福岡地所株式会社",
        "マスターリース会社": "本投資法人",
        "マスターリースの種別": "パススルー",
        "担保の状況": "無担保",
        "特記事項": "該当事項はありません。"
    }
}