{
    "日本橋プラヤビル": {
        "物件番号": "A-2"
    },
    "特定資産の概要": {
        "特定資産の種類": "不動産信託受益権",
        "信託受益権の概要": {
            "信託受託者": "みずほ信託銀行株式会社",
            "信託設定日": "2011年3月29日",
            "信託期間満了日": "2031年3月31日"
        },
        "取得年月日": "2011年3月29日",
        "取得価格": "2,130百万円",
        "所在地（住居表示）": "東京都中央区日本橋浜町一丁目9番12号",
        "土地": {
            "地番": "東京都中央区日本橋浜町\n一丁目4番13",
            "建蔽率": "100%(注)",
            "容積率": "500%",
            "用途地域": "商業地域",
            "敷地面積": "593.32㎡",
            "所有形態": "所有権"
        },
        "建物": {
            "竣工年月": "2009年2月",
            "構造／階数": "鉄骨造陸屋根7階建",
            "用途": "事務所",
            "延床面積": "2,956.10㎡",
            "駐車場台数": "7台",
            "所有形態": "所有権"
        },
        "PM会社": "双日ライフワン株式会社",
        "マスターリース会社": "本投資法人",
        "マスターリース種別": "パス・スルー",
        "特記事項": "該当事項はありません。",
        "タイトル未定義(1)": "(注)　建蔽率は本来80％ですが、商業地域・防火地域内の耐火建築物による緩和により100％となっています。"
    }
}