{
    "物件名称": "イオンモール太田",
    "区分（物件番号）": "RSC（RSC-4）",
    "特定資産の概要": {
        "特定資産の種類": "信託受益権",
        "建物状況評価の概要": {
            "調査業者": "東京海上ディーアール株式会社",
            "調査年月": "2018年６月",
            "緊急修繕費": "－千円",
            "短期修繕費": "－千円",
            "長期修繕費": "15年合計1,457,790千円\n年平均97,186千円"
        },
        "取得年月日": "2013年11月25日",
        "取得価額": "6,860百万円",
        "信託受益権の概要": {
            "信託設定日": "2013年11月25日",
            "信託受託者": "みずほ信託銀行株式会社",
            "信託期間満了日": "2033年11月30日"
        },
        "所在地": "群馬県太田市石原町81番地",
        "土地": {
            "敷地面積": "146,106.96㎡",
            "用途地域": "商業地域",
            "建ぺい率（注）": "70％",
            "容積率": "200％",
            "所有形態": "借地権"
        },
        "建物": {
            "竣工年月": "2003年11月17日",
            "構造・階数": "鉄骨造陸屋根５階建",
            "延床面積": "93,165.27㎡",
            "用途": "店舗",
            "所有形態": "所有権"
        },
        "担保設定の有無": "無",
        "PM会社": "イオンディライト株式会社",
        "マスターリース会社": "イオンモール株式会社",
        "タイトル未定義(1)": "特記事項\n該当事項はありません。"
    }
}