{
    "物件番号": "Ｍ-３",
    "ロジスクエア久喜Ⅱ": {
        "用途": "物流関連施設"
    },
    "特定資産の概要": {
        "特定資産の種類": "信託受益権",
        "信託受益権の概要": {
            "信託設定日": "2018年２月７日",
            "信託受託者": "三菱ＵＦＪ信託銀行株式会社",
            "信託期間満了日": "2038年２月28日"
        },
        "取得年月日": "2018年２月７日",
        "取得価格": "2,079,000,000円",
        "土地": {
            "所在地": "埼玉県久喜市八甫字前谷1390番地５",
            "面積": "9,846.41㎡",
            "用途地域": "指定なし（市街化調整区域）",
            "建蔽率／容積率": "60％（注）／200％",
            "所有形態": "所有権"
        },
        "建物": {
            "建物構造": "鉄骨造合金メッキ鋼板ぶき\n２階建",
            "竣工年月日": "2017年２月１日",
            "延床面積": "11,511.22㎡",
            "種類": "倉庫",
            "所有形態": "所有権"
        },
        "マスターリース会社": "－",
        "PM会社": "株式会社シーアールイー",
        "マスターリース契約": "－",
        "テナント数": "１",
        "タイトル未定義(1)": "特記事項：\n本建物建設時の本土地の所有者は、本土地に隣接する水路を管理する久喜市より、合併処理浄化槽排水及び雨水を当該水路に放流するために排水放流許可を取得しており、信託受託者は当該許可を承継しています。\n本土地の一部（約147㎡）は、都市計画道路（３・４・２大宮栗橋線、計画幅員21m（ただし、久喜市が計画する計画線と埼玉県が計画する計画線に相違があります。））区域内に存しています。事業決定はなされておらず、事業実施時期、収用面積等の詳細は未定です。"
    }
}