{
    "■　物件番号A12：　ダイエー宝塚中山店": {
        "運用資産の種類": "不動産を信託する信託の受益権",
        "構造・規模": "鉄骨造亜鉛メッキ鋼板葺地下1階付3階建\n（附属建物：鉄骨造陸屋根5階建）",
        "所在": {
            "地　　番": "兵庫県宝塚市売布東の町91番1他",
            "住居表示": "兵庫県宝塚市売布東の町21番22号"
        },
        "建築時期": "1997年11月",
        "取得年月日": "2008年1月30日",
        "取得価格": "4,284,000千円",
        "取得時の鑑定評価額": "4,360,000千円",
        "種類": "店舗（附属建物：駐車場）",
        "信託受託者": "三井住友信託銀行株式会社",
        "用途地域": "近隣商業地域／第一種中高層住居専用地域",
        "PM会社": "株式会社ダイエー",
        "容積率": "200％",
        "担保設定の有無": "無",
        "建ぺい率": "60％／80％",
        "代表的テナント": "株式会社ダイエー",
        "面積": "土地：16,330.14㎡　（4,939.86坪）（注）\n建物：16,729.60㎡　（5,060.70坪）\n（附属建物：929.40㎡）",
        "所有形態": "土地：所有権、借地権\n建物：所有権",
        "特記事項": "（権利関係等）\n・本物件に係る土地の一部に、公共下水道管の埋設及び維持管理を目的として、地役権が設定されています。\n（その他）\n・指定調査機関による本件土地に係る2007年1月の土壌環境調査報告書によれば、本物件に係る土地のほぼ全地点より鉛溶出量、砒素溶出量、ふっ素溶出量が指定基準を超過する濃度で確認されていますが、当該敷地内については、直接的な健康被害の可能性はないと考えられる旨記載されています。本投資法人は、将来土壌改良の必要が生じる場合に備え、信託受益権譲渡契約において、前所有者において将来の土壌改良に係る必要コストとして追加信託した630百万円を、本投資法人が本物件を取得するにあたり承継しています。\n（注）土地の面積については、借地部分（334㎡）も含めた敷地面積の合計を登記簿の記載に基づき記載しています。"
    }
}