{
    "取得日": "①②③2005年11月30日\n④2014年３月７日",
    "特定資産の種類": "①②③信託受益権\n④不動産",
    "取得価格": "①②③29,696,000千円\n④1,120,000千円",
    "信託受益権の概要": {
        "信託受託者": "三井住友信託銀行株式会社",
        "信託設定日": "2001年２月27日",
        "信託満了日": "2031年２月末日"
    },
    "取得時の鑑定評価額": "①②③29,700,000千円\n④1,300,000千円",
    "同　価格時点": "①②③2005年11月30日\n④2014年１月31日",
    "所在地": {
        "住居表示": "①東京都中央区佃一丁目11番６号\n②東京都中央区佃一丁目11番３号\n③東京都中央区佃一丁目11番２号\n④東京都中央区佃一丁目50番１（地番）"
    },
    "土地": {
        "建蔽率": "60％",
        "容積率": "400％",
        "用途地域": "第一種住居地域",
        "敷地面積": "30,291.75㎡",
        "所有形態": "①所有権\n（共有持分10,000,000分の2,319,274）\n②所有権\n（共有持分10,000,000分の860,005）\n③所有権\n（共有持分10,000,000分の162,397）\n④所有権\n（共有持分10,000,000分の1,926,003）"
    },
    "建物": {
        "竣工年月日": "①1989年３月30日\n②1988年７月19日新築、\n1989年３月30日増築\n③1988年４月４日\n④1989年３月30日新築、\n　1991年８月26日増築、\n　1993年２月23日増築",
        "構造／階数": "①鉄骨鉄筋コンクリート造陸屋根地下２階付40階建\n②鉄筋コンクリート・鉄骨鉄筋コンクリート造ルーフィング葺地下２階付14階建\n③鉄筋コンクリート造ルーフィング葺地下１階付２階建\n④鉄筋コンクリート・鉄骨鉄筋コンクリート造地下３階建",
        "用途": "①管理員控室・駐輪場・倉庫・塵芥室・居宅\n②倉庫・駐輪場・塵芥室・居宅\n③管理事務所\n④駐車場・ゴミ置場",
        "延床面積": "①42,177.83㎡\n②15,737.63㎡\n③847.27㎡\n④32,137.93㎡",
        "所有形態": "①②③④所有権\n（区分所有持分100％）",
        "賃貸可能戸数": "①390戸　②154戸　③なし"
    },
    "プロパティ・マネジメント会社": "三井不動産レジデンシャルリース株式会社",
    "マスターリース会社": "三井不動産レジデンシャルリース株式会社（注1）",
    "マスターリース種別": "パス・スルー",
    "前所有者": "①②③アール・ツー・ワン特定目的会社\n④三井不動産株式会社",
    "特記事項": "対象物件を含む大川端リバーシティ21の「西ブロック地区」全体（以下「西ブロック地区」といいます。）（注2）は、中央区の佃児童館及びシニアセンターの各用地と共に、総合的設計による一団地認定を受けています。",
    "備考": "賃貸住宅である「リバーポイントタワー」は、東京メトロ有楽町線・都営地下鉄大江戸線「月島」駅から徒歩７分、「パークサイド・ウィングス」は、同駅から徒歩６分"
}